{
  "sections": {
    "91e0f90e-ad97-458f-8ab1-a5b274e18a11": {
      "type": "slideshow",
      "blocks": {
        "template--21734502760741__91e0f90e-ad97-458f-8ab1-a5b274e18a11-img-1": {
          "type": "img",
          "settings": {
            "image_sl": "shopify:\/\/shop_images\/Frame_1000008055_88ca3156-4bee-4cff-9df6-8f1d1581dbff.png",
            "link_img": "",
            "open_link": "_self",
            "caption_w": "1",
            "h_position": "left",
            "v_position": "middle",
            "txt_align": "left"
          }
        },
        "hd_APyB9p": {
          "type": "hd",
          "settings": {
            "hide": false,
            "title": "Experience the freedom of <br>movement with Hitch Expo",
            "text_animate": "none",
            "text_time": 1.5,
            "color": "#111111",
            "linear_gradient": "",
            "fw_text": 600,
            "fs_text": 45,
            "lh_text": 45,
            "ls_text": "0",
            "font_style": "normal",
            "text_transform": "none",
            "first_mark": false,
            "last_mark": true,
            "custom_mark": "7",
            "color_mark": "#e5c33a",
            "mobile_fw_text": 600,
            "mobile_lh_text": 30,
            "mobile_font_text": 25
          }
        },
        "txt_gfznrw": {
          "type": "txt",
          "settings": {
            "title": "Whether you're on the road or planning the next adventure, our commitment<br> to quality and efficiency ensures that you're never left stranded.",
            "text_animate": "none",
            "text_time": 1.5,
            "color": "#111111",
            "fw_text": 400,
            "fs_text": 14,
            "lh_text": 0,
            "ls_text": 0,
            "hide": false,
            "hide_mobile": false,
            "mobile_fw_text": 400,
            "mobile_lh_text": 0,
            "mobile_font_text": 14
          }
        },
        "c_year_make_model_search_ymm_searchbox_pro_XpTRGe": {
          "type": "shopify:\/\/apps\/c-year-make-model-search\/blocks\/ymm-searchbox-pro\/ce35ea35-ef50-4f43-8cb6-7c34cae4c285",
          "settings": {
            "searchbox_title": "",
            "searchbox_style": "horizontal"
          }
        },
        "float_image_EknjB9": {
          "type": "float-image",
          "settings": {
            "float_image": "shopify:\/\/shop_images\/Frame_34029.png",
            "image_width": 150,
            "image_height": 350,
            "padding_top": 0
          }
        },
        "float_image_XkgUcc": {
          "type": "float-image",
          "settings": {
            "float_image": "shopify:\/\/shop_images\/Frame_34029_1.png",
            "image_width": 250,
            "image_height": 250,
            "padding_top": 0
          }
        },
        "float_image_GrcNGe": {
          "type": "float-image",
          "settings": {
            "float_image": "shopify:\/\/shop_images\/Frame_34030.png",
            "image_width": 250,
            "image_height": 550,
            "padding_top": 80
          }
        }
      },
      "block_order": [
        "template--21734502760741__91e0f90e-ad97-458f-8ab1-a5b274e18a11-img-1",
        "hd_APyB9p",
        "txt_gfznrw",
        "c_year_make_model_search_ymm_searchbox_pro_XpTRGe",
        "float_image_EknjB9",
        "float_image_XkgUcc",
        "float_image_GrcNGe"
      ],
      "settings": {
        "hidden": false,
        "h_des": "650px",
        "h_tb": "500px",
        "h_mb": "350px",
        "border": 10,
        "use-slider": false,
        "slides-To-Scroll": 1,
        "visible": 1,
        "widescreen": 1,
        "desktop": 1,
        "laptop": 1,
        "notebook": 1,
        "tablet": 1,
        "landscape": 1,
        "portrait": 1,
        "mobile": 1,
        "rows": 1,
        "autoplay": true,
        "speed": "300",
        "autoplay-Speed": "3000",
        "arrows": true,
        "fade": false,
        "fade_zoom": false,
        "center-Mode": false,
        "adaptive-Height": false,
        "dots": false,
        "infinite": false,
        "padding": 0,
        "vertical": false,
        "position_dots": "left",
        "style_dots": "default",
        "custom_width": false,
        "container_width": 1200,
        "layout": "full-width",
        "cl_bg": "#f5f5f5",
        "mg": "",
        "pd": "",
        "mg_mb": "",
        "pd_mb": ""
      }
    },
    "category_list_Q34gbK": {
      "type": "category-list",
      "blocks": {
        "category_tghRym": {
          "type": "category",
          "settings": {
            "category_title": "Trailer Hitches",
            "category_url": "shopify:\/\/collections\/trailer-hitches",
            "category_img": "shopify:\/\/shop_images\/Component_1_7.png",
            "category_clr": "#d2e0ff"
          }
        },
        "category_gGgiBF": {
          "type": "category",
          "settings": {
            "category_title": "Trailer Wiring",
            "category_url": "shopify:\/\/collections\/trailer-wiring",
            "category_img": "shopify:\/\/shop_images\/Component_1_2.png",
            "category_clr": "#fbeafe"
          }
        },
        "category_U3gNNe": {
          "type": "category",
          "settings": {
            "category_title": "Wiring Vehicle End",
            "category_url": "shopify:\/\/collections\/wiring-vehicle-end",
            "category_img": "shopify:\/\/shop_images\/Component_1_3.png",
            "category_clr": "#c1d6a7"
          }
        },
        "category_eMnhEF": {
          "type": "category",
          "settings": {
            "category_title": "Trailer Jacks",
            "category_url": "shopify:\/\/collections\/trailer-jacks",
            "category_img": "shopify:\/\/shop_images\/Component_1_4.png",
            "category_clr": "#eeedef"
          }
        },
        "category_t9KPr9": {
          "type": "category",
          "settings": {
            "category_title": "Fifth Wheel",
            "category_url": "shopify:\/\/collections\/fifth-wheel-accessories",
            "category_img": "shopify:\/\/shop_images\/Component_1_5_e4ad50a3-7334-4f13-b692-512f73c0a83f.png",
            "category_clr": "#ffe99d"
          }
        },
        "category_LXzcwd": {
          "type": "category",
          "settings": {
            "category_title": "Trailer Parts",
            "category_url": "shopify:\/\/collections\/trailer-parts",
            "category_img": "shopify:\/\/shop_images\/Component_1_6.png",
            "category_clr": "#f9c6ca"
          }
        },
        "category_PaBiD3": {
          "type": "category",
          "settings": {
            "category_title": "Accessories",
            "category_url": "shopify:\/\/collections\/accessories-parts",
            "category_img": "shopify:\/\/shop_images\/Component_1_3.png",
            "category_clr": "#d1e4fd"
          }
        }
      },
      "block_order": [
        "category_tghRym",
        "category_gGgiBF",
        "category_U3gNNe",
        "category_eMnhEF",
        "category_t9KPr9",
        "category_LXzcwd",
        "category_PaBiD3"
      ],
      "settings": {
        "title": "Shop by categories",
        "content": "",
        "enable_see_all": true,
        "see_all_text": "",
        "see_all_url": "",
        "padding-top": 50,
        "padding-bottom": 50
      }
    },
    "featured_collection_PkxFB3": {
      "type": "featured-collection",
      "settings": {
        "style": "style1",
        "title": "Our Latest Products",
        "content": "",
        "text_size": "medium",
        "text_transform": "none",
        "background_image": "shopify:\/\/shop_images\/Frame_1000008025.png",
        "collection": "our-latest-products",
        "max_count": 8,
        "use-slider": true,
        "slides-To-Scroll": 1,
        "visible": 3,
        "widescreen": 3,
        "desktop": 3,
        "laptop": 3,
        "notebook": 3,
        "tablet": 1,
        "landscape": 1,
        "portrait": 1,
        "mobile": 1,
        "rows": 1,
        "autoplay": false,
        "speed": "300",
        "autoplay-Speed": "3000",
        "arrows": false,
        "fade": false,
        "center-Mode": true,
        "adaptive-Height": false,
        "dots": true,
        "infinite": true,
        "padding": 15,
        "vertical": false,
        "layout_des": false,
        "cl_bg": "#ffffff",
        "mg": "",
        "pd": "50px,0,50px,0",
        "mg_mb": "",
        "pd_mb": "30px,0,30px,0"
      }
    },
    "collection_carousel_product_JafAVa": {
      "type": "collection-carousel-product",
      "settings": {
        "title": "Recommended products for you",
        "content": "",
        "text_size": "medium",
        "text_transform": "none",
        "enable_search": true,
        "collection": "draw-tite",
        "max_count": 8,
        "use-slider": false,
        "slides-To-Scroll": 1,
        "visible": 5,
        "widescreen": 4,
        "desktop": 4,
        "laptop": 4,
        "notebook": 3,
        "tablet": 3,
        "landscape": 3,
        "portrait": 3,
        "mobile": 3,
        "rows": 1,
        "autoplay": false,
        "speed": "300",
        "autoplay-Speed": "3000",
        "arrows": false,
        "fade": false,
        "center-Mode": false,
        "adaptive-Height": false,
        "dots": true,
        "infinite": false,
        "padding": 10,
        "vertical": false,
        "layout_des": false,
        "cl_bg": "#eceafe",
        "mg": "",
        "pd": "50px,0,50px,0",
        "mg_mb": "",
        "pd_mb": "30px,0,30px,0"
      }
    },
    "f886eb1d-f627-408c-b608-f2652dab3a54": {
      "type": "brand-list",
      "blocks": {
        "template--21734502760741__f886eb1d-f627-408c-b608-f2652dab3a54-brand-1": {
          "type": "brand",
          "settings": {
            "image": "shopify:\/\/shop_images\/image_10.png",
            "url": "shopify:\/\/collections\/bulldog",
            "open_link": "_blank"
          }
        },
        "template--21734502760741__f886eb1d-f627-408c-b608-f2652dab3a54-brand-2": {
          "type": "brand",
          "settings": {
            "image": "shopify:\/\/shop_images\/image_9.png",
            "url": "shopify:\/\/collections\/bargman",
            "open_link": "_blank"
          }
        },
        "template--21734502760741__f886eb1d-f627-408c-b608-f2652dab3a54-brand-3": {
          "type": "brand",
          "settings": {
            "image": "shopify:\/\/shop_images\/image_11.png",
            "url": "shopify:\/\/collections\/draw-tite",
            "open_link": "_blank"
          }
        },
        "template--21734502760741__f886eb1d-f627-408c-b608-f2652dab3a54-brand-4": {
          "type": "brand",
          "settings": {
            "image": "shopify:\/\/shop_images\/image_12.png",
            "url": "shopify:\/\/collections\/fulton",
            "open_link": "_blank"
          }
        },
        "brand_f6TcDG": {
          "type": "brand",
          "settings": {
            "image": "shopify:\/\/shop_images\/image_10_ecb6195d-0a8b-48d9-ae31-515c511ee880.png",
            "url": "shopify:\/\/collections\/bulldog",
            "open_link": "_blank"
          }
        },
        "brand_wYd6nD": {
          "type": "brand",
          "settings": {
            "image": "shopify:\/\/shop_images\/image_9_00b30f3a-450b-4513-a843-0b95fdafa9b2.png",
            "url": "shopify:\/\/collections\/bargman",
            "open_link": "_blank"
          }
        },
        "brand_DBnQgK": {
          "type": "brand",
          "settings": {
            "image": "shopify:\/\/shop_images\/image_12_376f5aa4-3f98-4d3c-9dcd-dd7e53155b80.png",
            "url": "shopify:\/\/collections\/fulton",
            "open_link": "_blank"
          }
        }
      },
      "block_order": [
        "template--21734502760741__f886eb1d-f627-408c-b608-f2652dab3a54-brand-1",
        "template--21734502760741__f886eb1d-f627-408c-b608-f2652dab3a54-brand-2",
        "template--21734502760741__f886eb1d-f627-408c-b608-f2652dab3a54-brand-3",
        "template--21734502760741__f886eb1d-f627-408c-b608-f2652dab3a54-brand-4",
        "brand_f6TcDG",
        "brand_wYd6nD",
        "brand_DBnQgK"
      ],
      "settings": {
        "title": "Our Top Brands",
        "sub_title": "",
        "hidden": false,
        "show_border_top": false,
        "use-slider": true,
        "slides-To-Scroll": 1,
        "visible": 5,
        "widescreen": 4,
        "desktop": 4,
        "laptop": 4,
        "notebook": 3,
        "tablet": 3,
        "landscape": 2,
        "portrait": 2,
        "mobile": 1,
        "rows": 1,
        "autoplay": false,
        "speed": "300",
        "autoplay-Speed": "3000",
        "arrows": true,
        "fade": false,
        "center-Mode": false,
        "adaptive-Height": false,
        "dots": true,
        "infinite": false,
        "padding": 10,
        "vertical": false,
        "show_view_all": false,
        "layout": false,
        "use_eq_height": false,
        "image_ratio": "ratio3_2",
        "cl_bg": "rgba(0,0,0,0)",
        "mg": "30px",
        "pd": "30px",
        "mg_mb": "15px",
        "pd_mb": "15px"
      }
    },
    "images_with_text_CLXYcP": {
      "type": "images-with-text",
      "blocks": {
        "subtext_XNATh6": {
          "type": "subtext",
          "settings": {
            "subtext": "Explore our first class services",
            "Sub_clr": "#4269f2"
          }
        },
        "title_xrYi74": {
          "type": "title",
          "settings": {
            "title": "Feel the best experience with<br> <span class=\"text-highlight_1\">HitchExpo.com<\/span>"
          }
        },
        "description_npw6Xd": {
          "type": "description",
          "settings": {
            "description": "<p>Lorem ipsum dolor sit amet consectetur. Duis in mauris dui ut. Nulla ullamcorper tempus volutpat viverra viverra aenean amet egestas neque.<\/p>"
          }
        },
        "icon_text_nUzwPp": {
          "type": "icon-text",
          "settings": {
            "icon": "shield",
            "title": "Variety of Brands",
            "description": "<p>Lorem ipsum dolor sit amet consectetur. Eget duis ac commodo viverra risus congue morbi dolor eu.<\/p>"
          }
        },
        "icon_text_NaCC8c": {
          "type": "icon-text",
          "settings": {
            "icon": "star",
            "title": "Top quality parts",
            "description": "<p>Lorem ipsum dolor sit amet consectetur. Eget duis ac commodo viverra risus congue morbi dolor eu.<\/p>"
          }
        },
        "icon_text_aKqiej": {
          "type": "icon-text",
          "settings": {
            "icon": "headphones",
            "title": "Customer-centric approach",
            "description": "<p>Lorem ipsum dolor sit amet consectetur. Eget duis ac commodo viverra risus congue morbi dolor eu.<\/p>"
          }
        },
        "icon_text_GXgLmk": {
          "type": "icon-text",
          "settings": {
            "icon": "lock",
            "title": "Secure system",
            "description": "<p>Lorem ipsum dolor sit amet consectetur. Eget duis ac commodo viverra risus congue morbi dolor eu.<\/p>"
          }
        }
      },
      "block_order": [
        "subtext_XNATh6",
        "title_xrYi74",
        "description_npw6Xd",
        "icon_text_nUzwPp",
        "icon_text_NaCC8c",
        "icon_text_aKqiej",
        "icon_text_GXgLmk"
      ],
      "settings": {
        "first_image": "shopify:\/\/shop_images\/image_49.png",
        "second_image": "shopify:\/\/shop_images\/image_48.png",
        "padding-top": 50,
        "padding-bottom": 50
      }
    },
    "f0c8c3b2-bdb1-46ea-89d2-52b13690ae34": {
      "type": "testimonials",
      "blocks": {
        "quote_iULVcb": {
          "type": "quote",
          "settings": {
            "content": "<p>Shopping on HitchExpo.com was a breeze! Found exactly what I needed in minutes.<\/p>",
            "title": "Sarah B.",
            "address": "Atlanta, GA",
            "rating": 5
          }
        },
        "template--18743199334685__f0c8c3b2-bdb1-46ea-89d2-52b13690ae34-1682585275ff3ad59b-2": {
          "type": "quote",
          "settings": {
            "content": "<p>The staff at hitch expo are truly experts. They helped me pick the perfect hitch<br\/>for my truck!<\/p>",
            "title": "Mike J.",
            "address": "Dallas, TX",
            "rating": 5
          }
        },
        "quote_WPwL3m": {
          "type": "quote",
          "settings": {
            "content": "<p>Quality products that I trust. Hitch Expo never disappoints.<\/p>",
            "title": "Emily R.",
            "address": "San Diego, CA",
            "rating": 5
          }
        },
        "template--18743199334685__f0c8c3b2-bdb1-46ea-89d2-52b13690ae34-1682585275ff3ad59b-1": {
          "type": "quote",
          "settings": {
            "content": "<p>After-sales support from HitchExpo.com is outstanding. They really care about their<br\/>customers<\/p>",
            "title": "David K.",
            "address": "Chicago, IL",
            "rating": 5
          }
        },
        "quote_gr979U": {
          "type": "quote",
          "settings": {
            "content": "<p>What a fun shopping experience! Hitch Expo has a great selection and easy navigation.<\/p>",
            "title": "Anna L.",
            "address": "Orlando, FL",
            "rating": 5
          }
        },
        "template--18743199334685__f0c8c3b2-bdb1-46ea-89d2-52b13690ae34-1682585275ff3ad59b-0": {
          "type": "quote",
          "settings": {
            "content": "<p>I can always count on hitchexpo.com for fast delivery and easy checkout.<\/p>",
            "title": "Greg P.",
            "address": "Seattle, WA",
            "rating": 5
          }
        },
        "quote_HCfEHp": {
          "type": "quote",
          "settings": {
            "content": "<p>The team at Hitch Expo is so approachable and knowledgeable. Made my purchase decision so much easier.\"<\/p>",
            "title": "Linda M.",
            "address": "Denver, CO",
            "rating": 5
          }
        },
        "quote_cVDjj8": {
          "type": "quote",
          "settings": {
            "content": "<p>I'm always impressed by the durable products I find on hitchexpo.com. Top-notch<br\/>brands!<\/p>",
            "title": "Jordan S.",
            "address": "Phoenix, AZ",
            "rating": 5
          }
        },
        "quote_kVHjmQ": {
          "type": "quote",
          "settings": {
            "content": "<p>Had a minor issue with my order, but Hitch Expo's customer service was on it and<br\/>resolved it quickly.<\/p>",
            "title": "Stephanie T.",
            "address": "Boston, MA",
            "rating": 5
          }
        },
        "quote_yAgzTn": {
          "type": "quote",
          "settings": {
            "content": "<p>Found some really unique accessories on hitchexpo.com that I couldn't find anywhere<br\/>else.<\/p>",
            "title": "Carlos E.",
            "address": "Houston, TX",
            "rating": 5
          }
        },
        "quote_eCpRAY": {
          "type": "quote",
          "settings": {
            "content": "<p>Checkout was a snap on HitchExpo.com! Highly recommend for a hassle-free<br\/>experience.\"<\/p>",
            "title": "Olivia V.",
            "address": "New York, NY",
            "rating": 5
          }
        },
        "quote_Dmit3L": {
          "type": "quote",
          "settings": {
            "content": "<p>You can tell the staff at Hitch Expo loves what they do. Their passion made the<br\/>shopping experience even better.<\/p>",
            "title": "Eric W.",
            "address": "Minneapolis, MN",
            "rating": 5
          }
        },
        "quote_rVmgkg": {
          "type": "quote",
          "settings": {
            "content": "<p>Trust is important to me, and Hitch Expo delivers with quality products every time.<\/p>",
            "title": "Naomi C.",
            "address": "Los Angeles, CA",
            "rating": 5
          }
        },
        "quote_VDQPem": {
          "type": "quote",
          "settings": {
            "content": "<p>The customer support at hitchexpo.com really went above and beyond when I had<br\/>questions.<\/p>",
            "title": "Keith D.",
            "address": "Philadelphia, PA",
            "rating": 5
          }
        },
        "quote_pTxh73": {
          "type": "quote",
          "settings": {
            "content": "<p>I was amazed at how quickly I found what I needed on Hitch Expo. Their site is so<br\/>user-friendly!<\/p>",
            "title": "Rachel F.",
            "address": "Miami, FL",
            "rating": 5
          }
        },
        "quote_VBmEwW": {
          "type": "quote",
          "settings": {
            "content": "<p>HitchExpo.com's fast shipping had my order at my door in no time!<\/p>",
            "title": "Tony G.",
            "address": "Las Vegas, NV",
            "rating": 5
          }
        },
        "quote_pncJDK": {
          "type": "quote",
          "settings": {
            "content": "<p>The expertise of Hitch Expo's staff made me feel confident in my purchase.<\/p>",
            "title": "Jessica H.",
            "address": "San Francisco, CA",
            "rating": 5
          }
        },
        "quote_CdGPWz": {
          "type": "quote",
          "settings": {
            "content": "<p>I always recommend hitchexpo.com for their unbeatable quality and selection.<\/p>",
            "title": "Diane I.",
            "address": "Baltimore, MD",
            "rating": 5
          }
        },
        "quote_xTLE7A": {
          "type": "quote",
          "settings": {
            "content": "<p>The post-purchase support from Hitch Expo is just as impressive as their product<br\/>lineup.<\/p>",
            "title": "Brandon J.",
            "address": "Kansas City, MO",
            "rating": 5
          }
        },
        "quote_JL9q3F": {
          "type": "quote",
          "settings": {
            "content": "<p>Discovered some great deals on hitchexpo.com. Their prices are unbeatable.<\/p>",
            "title": "Chloe K.",
            "address": "Louis, MO",
            "rating": 5
          }
        },
        "quote_fth3aN": {
          "type": "quote",
          "settings": {
            "content": "<p>The simplicity of shopping on HitchExpo.com is unmatched. Found what I needed in no<br\/>time!<\/p>",
            "title": "Luke L.",
            "address": "Columbus, OH",
            "rating": 5
          }
        },
        "quote_PEdhtX": {
          "type": "quote",
          "settings": {
            "content": "<p>Really felt like the staff at Hitch Expo listened and understood my needs.<\/p>",
            "title": "Megan M.",
            "address": "Charlotte, NC",
            "rating": 5
          }
        },
        "quote_CbiNA3": {
          "type": "quote",
          "settings": {
            "content": "<p>Every product I've bought from hitchexpo.com has been of the highest quality.<\/p>",
            "title": "Noah N.",
            "address": "Salt Lake City, UT",
            "rating": 5
          }
        },
        "quote_DqEBCq": {
          "type": "quote",
          "settings": {
            "content": "<p>Customer service at Hitch Expo is top-tier. They truly value their customers.<\/p>",
            "title": "Hailey O.",
            "address": "Milwaukee, WI",
            "rating": 5
          }
        },
        "quote_JaaW88": {
          "type": "quote",
          "settings": {
            "content": "<p>I love the variety on hitchexpo.com. There's something for every type of vehicle.<\/p>",
            "title": "Peyton P.",
            "address": "Nashville, TN",
            "rating": 5
          }
        },
        "quote_Rc368M": {
          "type": "quote",
          "settings": {
            "content": "<p>HitchExpo.com made my shopping experience so smooth and enjoyable.<\/p>",
            "title": "Quinn R.",
            "address": "Omaha, NE",
            "rating": 5
          }
        },
        "quote_WrJTWa": {
          "type": "quote",
          "settings": {
            "content": "<p>The friendly staff at Hitch Expo made me feel like a VIP.<\/p>",
            "title": "Riley S.",
            "address": "Cincinnati, OH",
            "rating": 5
          }
        },
        "quote_tpF8pf": {
          "type": "quote",
          "settings": {
            "content": "<p>I trust the brands hitchexpo.com carries. They've never let me down.<\/p>",
            "title": "Taylor T.",
            "address": "Raleigh, NC",
            "rating": 5
          }
        }
      },
      "block_order": [
        "quote_iULVcb",
        "template--18743199334685__f0c8c3b2-bdb1-46ea-89d2-52b13690ae34-1682585275ff3ad59b-2",
        "quote_WPwL3m",
        "template--18743199334685__f0c8c3b2-bdb1-46ea-89d2-52b13690ae34-1682585275ff3ad59b-1",
        "quote_gr979U",
        "template--18743199334685__f0c8c3b2-bdb1-46ea-89d2-52b13690ae34-1682585275ff3ad59b-0",
        "quote_HCfEHp",
        "quote_cVDjj8",
        "quote_kVHjmQ",
        "quote_yAgzTn",
        "quote_eCpRAY",
        "quote_Dmit3L",
        "quote_rVmgkg",
        "quote_VDQPem",
        "quote_pTxh73",
        "quote_VBmEwW",
        "quote_pncJDK",
        "quote_CdGPWz",
        "quote_xTLE7A",
        "quote_JL9q3F",
        "quote_fth3aN",
        "quote_PEdhtX",
        "quote_CbiNA3",
        "quote_DqEBCq",
        "quote_JaaW88",
        "quote_Rc368M",
        "quote_WrJTWa",
        "quote_tpF8pf"
      ],
      "custom_css": [

      ],
      "settings": {
        "title": "What Our Customers Are Saying.",
        "content": "",
        "text_size": "large",
        "text_transform": "none",
        "show_text_bottom": true,
        "text_bottom": "",
        "hidden": false,
        "layout": "container",
        "width_c": 90,
        "style": "style3",
        "use-slider": true,
        "slides-To-Scroll": 1,
        "visible": 3,
        "widescreen": 3,
        "desktop": 3,
        "laptop": 3,
        "notebook": 3,
        "tablet": 1,
        "landscape": 1,
        "portrait": 1,
        "mobile": 1,
        "rows": 1,
        "autoplay": true,
        "speed": "300",
        "autoplay-Speed": "3000",
        "arrows": true,
        "fade": false,
        "center-Mode": true,
        "adaptive-Height": true,
        "dots": true,
        "infinite": true,
        "padding": 10,
        "vertical": false,
        "cl_bg": "#f5f7fe",
        "mg": "",
        "pd": "60px,0,60px,0",
        "mg_mb": "",
        "pd_mb": "30px,0,30px,0"
      }
    },
    "text_column_with_image_YqYpVW": {
      "type": "text-column-with-image",
      "blocks": {
        "text_block_BbBLmb": {
          "type": "text_block",
          "settings": {
            "enable_image": false,
            "enable_icon": true,
            "icon": "truck",
            "title": "Nationwide shipping",
            "sub_title": "",
            "text": "<p>Swift & complimentary delivery across all 50 states.<\/p>",
            "btn_title": "",
            "btn_link": "",
            "open_link": "_blank"
          }
        },
        "text_block_7nzBX8": {
          "type": "text_block",
          "settings": {
            "enable_image": false,
            "enable_icon": true,
            "icon": "check-circle",
            "title": "Expert assistance",
            "sub_title": "",
            "text": "<p>Dedicated tech support available for fit and installation inquiries<\/p>",
            "btn_title": "",
            "btn_link": "",
            "open_link": "_blank"
          }
        },
        "text_block_YHGVeY": {
          "type": "text_block",
          "settings": {
            "enable_image": false,
            "enable_icon": true,
            "icon": "shield",
            "title": "Trusted quality",
            "sub_title": "",
            "text": "<p>Premium products from proven and reliable brands<\/p>",
            "btn_title": "",
            "btn_link": "",
            "open_link": "_blank"
          }
        },
        "text_block_Cp7EgY": {
          "type": "text_block",
          "settings": {
            "enable_image": false,
            "enable_icon": true,
            "icon": "layers",
            "title": "Precision fitment",
            "sub_title": "",
            "text": "<p>Up-to-date product information to guarantee the perfect fit for your vehicle<\/p>",
            "btn_title": "",
            "btn_link": "",
            "open_link": "_blank"
          }
        }
      },
      "block_order": [
        "text_block_BbBLmb",
        "text_block_7nzBX8",
        "text_block_YHGVeY",
        "text_block_Cp7EgY"
      ],
      "settings": {
        "hidden": false,
        "style": "box",
        "title": "",
        "sub_title": "",
        "content": "",
        "use-slider": false,
        "slides-To-Scroll": 1,
        "visible": 5,
        "widescreen": 4,
        "desktop": 4,
        "laptop": 4,
        "notebook": 4,
        "tablet": 3,
        "landscape": 1,
        "portrait": 1,
        "mobile": 1,
        "rows": 1,
        "autoplay": true,
        "speed": "300",
        "autoplay-Speed": "3000",
        "arrows": true,
        "fade": false,
        "center-Mode": false,
        "adaptive-Height": false,
        "dots": false,
        "infinite": false,
        "padding": 10,
        "vertical": false,
        "layout": "container",
        "cl_bg": "#20309c",
        "cl_text": "#ffffff",
        "mg": "",
        "pd": "50px,,50px",
        "mg_mb": "",
        "pd_mb": ""
      }
    },
    "69805983-b566-42af-ba6f-ca890638160a": {
      "type": "faq-sections",
      "blocks": {
        "template--21734502760741__69805983-b566-42af-ba6f-ca890638160a-faq-1": {
          "type": "faq",
          "settings": {
            "title": "Why is Hitch Expo?",
            "text": "<p>Curabitur lacinia purus vitae lorem porttitor fermentum. In in mattis erat mattis libero. Donec volutpat faucibus elit cursus interdum. Class aptent taciti sociosqu ad litora torquent per conubia nostra, per inceptos himenaeos.<\/p>",
            "link": "shopify:\/\/policies\/contact-information",
            "open_link": "_self"
          }
        },
        "template--21734502760741__69805983-b566-42af-ba6f-ca890638160a-faq-2": {
          "type": "faq",
          "settings": {
            "title": "What Is the Payment Process For Buying a Product?",
            "text": "<p>Curabitur lacinia purus vitae lorem porttitor fermentum. In in mattis erat mattis libero. Donec volutpat faucibus elit cursus interdum. Class aptent taciti sociosqu ad litora torquent per conubia nostra, per inceptos himenaeos.<\/p>",
            "link": "",
            "open_link": "_self"
          }
        },
        "template--21734502760741__69805983-b566-42af-ba6f-ca890638160a-faq-3": {
          "type": "faq",
          "settings": {
            "title": "What is your cancellation and Refund policy",
            "text": "",
            "link": "shopify:\/\/policies\/refund-policy",
            "open_link": "_self"
          }
        }
      },
      "block_order": [
        "template--21734502760741__69805983-b566-42af-ba6f-ca890638160a-faq-1",
        "template--21734502760741__69805983-b566-42af-ba6f-ca890638160a-faq-2",
        "template--21734502760741__69805983-b566-42af-ba6f-ca890638160a-faq-3"
      ],
      "settings": {
        "hidden": false,
        "hidden_newletter": false,
        "title": "Got a question for Hitch Expo?",
        "sub_title": "",
        "content": "Class aptent taciti sociosqu ad litora torquent per conubia nostra per inceptos vel pretium",
        "layout": "container",
        "cl_bg": "#faf6f0",
        "mg": "",
        "pd": "60px,,60px",
        "mg_mb": "",
        "pd_mb": "30px,,30px"
      }
    }
  },
  "order": [
    "91e0f90e-ad97-458f-8ab1-a5b274e18a11",
    "category_list_Q34gbK",
    "featured_collection_PkxFB3",
    "collection_carousel_product_JafAVa",
    "f886eb1d-f627-408c-b608-f2652dab3a54",
    "images_with_text_CLXYcP",
    "f0c8c3b2-bdb1-46ea-89d2-52b13690ae34",
    "text_column_with_image_YqYpVW",
    "69805983-b566-42af-ba6f-ca890638160a"
  ]
}
