{
  "sections": {
    "breadcrumb": {
      "type": "breadcrumb",
      "disabled": true,
      "settings": {
        "show_title_page": true,
        "h_position": "center",
        "v_position": "middle",
        "txt_align": "center",
        "bg": "#f7f7f9",
        "cl_title": "#212529",
        "cl_breadcrum": "#8d979e",
        "b_height": 200,
        "mg_bottom": 0,
        "mobile_bg": "#f5f5f5",
        "mobile_ht": 100,
        "mobile_mg_bottom": 0
      }
    },
    "main": {
      "type": "ymm-search-result",
      "blocks": {
        "category_bjHqp9": {
          "type": "category",
          "settings": {
            "title": "Trailer Hitches",
            "image": "shopify:\/\/shop_images\/Component_1_1.png",
            "url": "shopify:\/\/collections\/rear-trailer-hitches",
            "bg_color": "#ced9ff"
          }
        },
        "category_9M4KRV": {
          "type": "category",
          "settings": {
            "title": "Trailer Wiring",
            "image": "shopify:\/\/shop_images\/Component_1_2.png",
            "url": "shopify:\/\/collections\/trailer-wiring",
            "bg_color": "#ced9ff"
          }
        },
        "category_GeTVck": {
          "type": "category",
          "settings": {
            "title": "Wiring Vehicle End",
            "image": "shopify:\/\/shop_images\/Component_1_3.png",
            "url": "shopify:\/\/collections\/wiring-vehicle-end",
            "bg_color": "#ced9ff"
          }
        },
        "category_CW99rh": {
          "type": "category",
          "settings": {
            "title": "Trailer Jacks",
            "image": "shopify:\/\/shop_images\/Component_1_4.png",
            "url": "shopify:\/\/collections\/trailer-jacks",
            "bg_color": "#ced9ff"
          }
        },
        "category_r9drDD": {
          "type": "category",
          "settings": {
            "title": "Trailer Jacks",
            "image": "shopify:\/\/shop_images\/Component_1_4.png",
            "url": "shopify:\/\/collections\/trailer-jacks",
            "bg_color": "#ced9ff"
          }
        },
        "category_CHKFDL": {
          "type": "category",
          "settings": {
            "title": "Fifth Wheel",
            "image": "shopify:\/\/shop_images\/Component_1_5_e4ad50a3-7334-4f13-b692-512f73c0a83f.png",
            "url": "shopify:\/\/collections\/fifth-wheel-accessories",
            "bg_color": "#ced9ff"
          }
        },
        "category_fJBfPk": {
          "type": "category",
          "settings": {
            "title": "Trailer Parts",
            "image": "shopify:\/\/shop_images\/Component_1_6.png",
            "url": "shopify:\/\/collections\/trailer-parts",
            "bg_color": "#ced9ff"
          }
        },
        "category_fFe48H": {
          "type": "category",
          "settings": {
            "title": "Accessories",
            "image": "shopify:\/\/shop_images\/Component_1_3.png",
            "url": "shopify:\/\/collections\/accessories-parts",
            "bg_color": "#ced9ff"
          }
        }
      },
      "block_order": [
        "category_bjHqp9",
        "category_9M4KRV",
        "category_GeTVck",
        "category_CW99rh",
        "category_r9drDD",
        "category_CHKFDL",
        "category_fJBfPk",
        "category_fFe48H"
      ],
      "settings": {
        "pagination_limit": 18,
        "grid_list": "4",
        "visible": 3,
        "widescreen": 3,
        "desktop": 3,
        "laptop": 3,
        "notebook": 3,
        "tablet": 3,
        "landscape": 2,
        "portrait": 2,
        "mobile": 1,
        "card_style": "style_2",
        "padding_lr": 10,
        "enable_filtering": true,
        "filter_type": "horizontal",
        "enable_sorting": true,
        "enable_related_search": true,
        "cl_bg": "#fafafa",
        "mg": "",
        "pd": "30px,0,30px,0",
        "mg_mb": "",
        "pd_mb": "50px,0,50px,0"
      }
    },
    "faq_sections_QCA7zL": {
      "type": "faq-sections",
      "blocks": {
        "faq_MxLtaV": {
          "type": "faq",
          "settings": {
            "title": "What makes HitchExpo.com different?",
            "text": "<p>Rooted in tradition, our family-owned business brings over 50 years of combined expertise in industry know-how and unparalleled customer service. We're proud to offer products from trusted household names, ensuring quality and reliability in every purchase. Plus, our dedicated customer service team, based entirely in the U.S., is here for you around the clock, whether you prefer phone, email, or chat. Experience the difference that personal touch and<br\/>professional dedication make.<\/p>",
            "link": "",
            "open_link": "_self"
          }
        },
        "faq_9UKkMb": {
          "type": "faq",
          "settings": {
            "title": "What is the buying process?",
            "text": "<p>Step into a buying experience where simplicity meets security. Our checkout is a breeze and 100% secure, giving you peace of mind with every click. Rest easy knowing every product is manufacturer-verified for a perfect fit with your vehicle. Prefer a personal touch? Our 100% US-based customer service team is just a phone call away, ready to help!<\/p>",
            "link": "",
            "open_link": "_self"
          }
        },
        "faq_4BGJGn": {
          "type": "faq",
          "settings": {
            "title": "What Is Your Shipping and Refunds Policy?",
            "text": "<p>Experience the gold standard with our industry-leading shipping and returns policy. As a family-owned business, we take pride in offering free shipping across the country without any minimum purchase requirements, coupled with a generous 30-day return policy for any issues stemming from our side. Check our return\/refund policy for more insights and enjoy shopping with confidence!<\/p>",
            "link": "",
            "open_link": "_self"
          }
        }
      },
      "block_order": [
        "faq_MxLtaV",
        "faq_9UKkMb",
        "faq_4BGJGn"
      ],
      "disabled": true,
      "settings": {
        "hidden": false,
        "hidden_newletter": false,
        "title": "You have questions. We have answers.",
        "sub_title": "",
        "content": "Order updates? Product or service questions? Comments and Feedback? Our friendly team of experts is here to help. <br>\n<div>\n<a href=\"mailto:info@hitchexpo.com?subject=HitchExpo.com%20Question\">Contact Us: info@hitchexpo.com<\/a>\n<\/div>\n\n<div>\n  <br>  <span style=\"font-style: italic;\">Subscribe today for exclusive deals and updates!<\/span>\n<\/div>",
        "layout": "container",
        "cl_bg": "#fffbf5",
        "mg": "",
        "pd": "50px,0,50px,0",
        "mg_mb": "",
        "pd_mb": ""
      }
    }
  },
  "order": [
    "breadcrumb",
    "main",
    "faq_sections_QCA7zL"
  ]
}
