{
  "sections": {
    "main": {
      "type": "main-product",
      "blocks": {
        "ed5dec54-d995-4f88-87d3-102460e07067": {
          "type": "name_product",
          "settings": {
            "np_text_transform": "none",
            "np_size": 24,
            "np_weight": 500,
            "np_size_mobile": 24,
            "np_mg_top": 0,
            "np_mg_bottom": 10
          }
        },
        "8673dd22-d473-4cf2-a24f-a2c822dbbd0e": {
          "type": "shopify:\/\/apps\/judge-me-reviews\/blocks\/preview_badge\/61ccd3b1-a9f2-4160-9fe9-4fec8413e5d8",
          "settings": {
          }
        },
        "993a628c-32eb-456f-9eb4-88c3a61fa8e0": {
          "type": "product_infor",
          "settings": {
            "show_sku": true,
            "show_barcode": true,
            "show_vendor": true,
            "show_type": true,
            "show_availability": false,
            "color_in_stock": "#008a00",
            "color_out_stock": "#dd3842",
            "show_category": false,
            "limit_cate": 2,
            "show_tags": false,
            "limit_tags": 5
          }
        },
        "f1e09af0-0154-41e2-996f-755cdde44ea4": {
          "type": "show_price",
          "settings": {
            "show_discount": false
          }
        },
        "payment_terms_LmkiqF": {
          "type": "payment-terms",
          "settings": {
            "title": "Promotions"
          }
        },
        "c78dd46d-d065-4e43-aaa7-13423da0532f": {
          "type": "show_description",
          "settings": {
            "custom_liquid": "{{product.metafields.custom.short_description}}"
          }
        },
        "8681d35e-2735-4d23-98a5-4f3b5271e474": {
          "type": "quantity_button",
          "settings": {
            "icon_button_cart": "shopping-cart",
            "qt_show_quantity": true,
            "qt_show_cart": true,
            "show_popup": false,
            "product_terms_conditions_page_content": "terms-and-conditions",
            "qt_buy_it_now": true,
            "btn_affiliate": "",
            "qt_show_compare": false,
            "qt_show_wishlist": false,
            "show_social_sharing": false,
            "show_custom_color_btn": true,
            "color_text_cart": "#212121",
            "bg_add_to_cart": "#ffffff",
            "color_text_cart_hover": "#ffffff",
            "bg_add_to_cart_hv": "#232321",
            "color_text_buy_now": "#242121",
            "bg_buy_it_now": "#ffffff",
            "color_text_buy_now_hover": "#232020",
            "bg_buy_it_now_hv": "#caa923"
          }
        },
        "26205a69-31b8-41d3-83bf-2e25db4c4dfa": {
          "type": "shipping",
          "settings": {
            "show_delivery_times": true,
            "deliver_text": "Estimated Delivery:",
            "deliver_days": "7",
            "date_format": "%b %d",
            "show_shipping_text": true,
            "shipping_text": "<p>Return within <strong>30 days<\/strong> of purchase. Taxes are non-refundable.<\/p>"
          }
        },
        "f0b169ef-ed96-4dd1-9b76-7e2e8121cc42": {
          "type": "custom_html",
          "settings": {
            "html_custom": "Guarantee safe &amp; Secure checkout",
            "show_svg_custom": false,
            "svg_custom": "amazon_payments,american_express,apple_pay,bitcoin,dankort,diners_club,discover,dogecoin,dwolla,forbrugsforeningen,interac,google_pay,jcb,klarna,klarna-pay-later,litecoin,maestro,master,paypal,shopify_pay,sofort,visa",
            "svg_height": 35
          }
        },
        "303e9ab8-e392-40c7-9a5c-0e0198af5bed": {
          "type": "product_variants",
          "settings": {
            "show_title": true,
            "show_size_guide": true,
            "size_guide_page": "nevada-trailer-towing-laws"
          }
        }
      },
      "block_order": [
        "ed5dec54-d995-4f88-87d3-102460e07067",
        "8673dd22-d473-4cf2-a24f-a2c822dbbd0e",
        "993a628c-32eb-456f-9eb4-88c3a61fa8e0",
        "f1e09af0-0154-41e2-996f-755cdde44ea4",
        "payment_terms_LmkiqF",
        "c78dd46d-d065-4e43-aaa7-13423da0532f",
        "8681d35e-2735-4d23-98a5-4f3b5271e474",
        "26205a69-31b8-41d3-83bf-2e25db4c4dfa",
        "f0b169ef-ed96-4dd1-9b76-7e2e8121cc42",
        "303e9ab8-e392-40c7-9a5c-0e0198af5bed"
      ],
      "settings": {
        "cl_bg": "#ffffff",
        "mg": "0,0,30px,0",
        "pd": "40px,0,40px,0",
        "bd": "5px 5px 5px 5px",
        "mg_mb": "0,0,15px,0",
        "pd_mb": "10px,0,10px,0"
      }
    },
    "product-page-tab": {
      "type": "product-page-tab",
      "blocks": {
        "f9332aee-ca1e-4993-ad5c-e3d5984789cc": {
          "type": "tab_description",
          "settings": {
            "title_description": "Description"
          }
        },
        "22f75249-e4ab-453e-84d5-0006118d5803": {
          "type": "tab_metafields",
          "settings": {
            "title": "Additional Information",
            "custom_liquid": "{{product.metafields.custom.additional_information_new}}"
          }
        },
        "d07132a9-cf30-4c47-a9f5-6b3bd410c124": {
          "type": "tab_custom_html",
          "settings": {
            "title": "Shipping & Return",
            "page_content": "shipping-return"
          }
        },
        "0e2c2c01-948c-43f1-ae77-e8dbabaf8f55": {
          "type": "tab_reviews",
          "settings": {
            "title_reviews": "Reviews"
          }
        }
      },
      "block_order": [
        "f9332aee-ca1e-4993-ad5c-e3d5984789cc",
        "22f75249-e4ab-453e-84d5-0006118d5803",
        "d07132a9-cf30-4c47-a9f5-6b3bd410c124",
        "0e2c2c01-948c-43f1-ae77-e8dbabaf8f55"
      ],
      "settings": {
        "hide_tabs": false,
        "accordion_tabs": false,
        "cl_bg": "#ffffff",
        "mg": "0,0,60px,0",
        "pd": "40px,0,40px,0",
        "bd": "5px 5px 5px 5px",
        "mg_mb": "0,0,15px,0",
        "pd_mb": "10px,0,10px,0"
      }
    },
    "170401789281e0ae28": {
      "type": "apps",
      "blocks": {
        "808d3f3e-6347-478b-9359-1c8867f7cb4a": {
          "type": "shopify:\/\/apps\/c-year-make-model-search\/blocks\/ymm-compatible-list\/ce35ea35-ef50-4f43-8cb6-7c34cae4c285",
          "settings": {
          }
        },
        "44b6611c-a283-4f35-8cb2-5f94425bf1a6": {
          "type": "shopify:\/\/apps\/glo-related-products-upsell\/blocks\/app-block-product\/75cf2d86-3988-45e7-8f28-ada23c99704f",
          "settings": {
            "widget": "3",
            "gashortcode": ""
          }
        },
        "0f47da22-0600-4505-9814-4a21b2180a6c": {
          "type": "shopify:\/\/apps\/fether\/blocks\/widget-block\/f96a0d1a-35b8-40ef-ad54-1cb7fb011e11",
          "settings": {
          }
        },
        "0f23e87c-0f0b-4162-84e7-6f394d508fd1": {
          "type": "shopify:\/\/apps\/judge-me-reviews\/blocks\/verified_badge\/61ccd3b1-a9f2-4160-9fe9-4fec8413e5d8",
          "settings": {
          }
        },
        "7f8c0966-c681-4024-aa97-ccee168fefc3": {
          "type": "shopify:\/\/apps\/judge-me-reviews\/blocks\/review_widget\/61ccd3b1-a9f2-4160-9fe9-4fec8413e5d8",
          "settings": {
          }
        },
        "831f6b72-1c56-4548-8831-bacaee1e3c2b": {
          "type": "shopify:\/\/apps\/judge-me-reviews\/blocks\/featured_carousel\/61ccd3b1-a9f2-4160-9fe9-4fec8413e5d8",
          "settings": {
            "maxwidth": 1080
          }
        }
      },
      "block_order": [
        "808d3f3e-6347-478b-9359-1c8867f7cb4a",
        "44b6611c-a283-4f35-8cb2-5f94425bf1a6",
        "0f47da22-0600-4505-9814-4a21b2180a6c",
        "0f23e87c-0f0b-4162-84e7-6f394d508fd1",
        "7f8c0966-c681-4024-aa97-ccee168fefc3",
        "831f6b72-1c56-4548-8831-bacaee1e3c2b"
      ],
      "settings": {
      }
    },
    "2a5d30e1-b228-482c-b9c1-a26c5a513369": {
      "type": "faq-sections",
      "blocks": {
        "bda9d53a-09a5-4246-91a6-7d51b110ee6b": {
          "type": "faq",
          "settings": {
            "title": "How can I buy this product with EMI",
            "text": "<p>Curabitur lacinia purus vitae lorem porttitor fermentum. In in mattis erat mattis libero. Donec volutpat faucibus elit cursus interdum. <\/p>",
            "link": "shopify:\/\/pages\/tennessee-trailer-and-towing-laws",
            "open_link": "_blank"
          }
        },
        "7664f35b-beab-4ac7-b5c5-643621883faa": {
          "type": "faq",
          "settings": {
            "title": "How can I buy this product with EMI",
            "text": "<p>Curabitur lacinia purus vitae lorem porttitor fermentum. In in mattis erat mattis libero. Donec volutpat faucibus elit cursus interdum. Class aptent taciti sociosqu ad litora torquent per conubia nostra, per inceptos himenaeos.<\/p>",
            "link": "",
            "open_link": "_blank"
          }
        },
        "c6d6f686-5a7b-4389-88ea-b36fb9ee4050": {
          "type": "faq",
          "settings": {
            "title": "How can I buy this product with EMI",
            "text": "<p>Curabitur lacinia purus vitae lorem porttitor fermentum. In in mattis erat mattis libero. Donec volutpat faucibus elit cursus interdum. Class aptent taciti sociosqu ad litora torquent per conubia nostra, per inceptos himenaeos.<\/p>",
            "link": "",
            "open_link": "_blank"
          }
        }
      },
      "block_order": [
        "bda9d53a-09a5-4246-91a6-7d51b110ee6b",
        "7664f35b-beab-4ac7-b5c5-643621883faa",
        "c6d6f686-5a7b-4389-88ea-b36fb9ee4050"
      ],
      "settings": {
        "hidden": false,
        "title": "Frequently Asked Questions",
        "sub_title": "",
        "content": "",
        "layout": "container",
        "cl_bg": "#ffffff",
        "mg": "",
        "pd": "",
        "mg_mb": "",
        "pd_mb": ""
      }
    },
    "41693b03-89c2-4721-a0d0-03a59b3d98f1": {
      "type": "featured_blog",
      "settings": {
        "hidden": false,
        "title": "Question and Answer",
        "text_size": "large",
        "blog": "towing-with-trust-a-hitchexpo-guide",
        "show-cate-blog": true,
        "show-post-info": true,
        "show-name-blog": true,
        "show-description": true,
        "show-read_more": true,
        "use-slider": true,
        "slides-To-Scroll": 1,
        "visible": 5,
        "widescreen": 4,
        "desktop": 4,
        "laptop": 4,
        "notebook": 3,
        "tablet": 3,
        "landscape": 2,
        "portrait": 2,
        "mobile": 1,
        "rows": 1,
        "autoplay": true,
        "speed": "300",
        "autoplay-Speed": "3000",
        "arrows": true,
        "fade": false,
        "center-Mode": false,
        "adaptive-Height": false,
        "dots": false,
        "infinite": false,
        "padding": 10,
        "vertical": true,
        "show_view_all": false,
        "layout": "container",
        "use_eq_height": false,
        "image_ratio": "ratio3_2",
        "cl_bg": "#ffffff",
        "mg": "",
        "pd": "",
        "mg_mb": "",
        "pd_mb": ""
      }
    },
    "170659979689fff3f0": {
      "type": "apps",
      "blocks": {
        "judge_me_reviews_review_widget_hC3VDN": {
          "type": "shopify:\/\/apps\/judge-me-reviews\/blocks\/review_widget\/61ccd3b1-a9f2-4160-9fe9-4fec8413e5d8",
          "settings": {
          }
        }
      },
      "block_order": [
        "judge_me_reviews_review_widget_hC3VDN"
      ],
      "settings": {
      }
    }
  },
  "order": [
    "main",
    "product-page-tab",
    "170401789281e0ae28",
    "2a5d30e1-b228-482c-b9c1-a26c5a513369",
    "41693b03-89c2-4721-a0d0-03a59b3d98f1",
    "170659979689fff3f0"
  ]
}
